tornad_io
