Metadata-Version: 1.1
Name: SocketTornad.IO
Version: 0.1.3
Summary: Python implementation of the Socket.IO protocol for the Tornado webserver/framework.
Home-page: http://github.com/SocketTornadIO/SocketTornad.IO
Author: Brendan W. McAdams
Author-email: bwmcadams@evilmonkeylabs.com
License: Copyright (c) 2010, Brendan W. McAdams & Novus Partners, Inc. <http://novus.com> 
